LICENSE
MANIFEST.in
README.md
requirements.txt
setup.py
google_hangouts_chat_bot/commands.py
google_hangouts_chat_bot/event_handler.py
google_hangouts_chat_bot/parser.py
google_hangouts_chat_bot/responses.py
google_hangouts_chat_bot/security.py
google_hangouts_chat_bot/version.py
google_hangouts_chat_bot.egg-info/PKG-INFO
google_hangouts_chat_bot.egg-info/SOURCES.txt
google_hangouts_chat_bot.egg-info/dependency_links.txt
google_hangouts_chat_bot.egg-info/requires.txt
google_hangouts_chat_bot.egg-info/top_level.txt