Metadata-Version: 2.1
Name: google-hangouts-chat-bot
Version: 0.1.5
Summary: A framework for Google Hangouts Chat Bot
Home-page: https://github.com/ciandt/google-hangouts-chat-bot
Author: Jean Pimentel
Author-email: contato@jeanpimentel.com.br
License: MIT
Keywords: google hangouts chat chatbot
Platform: UNKNOWN
Classifier: Development Status :: 3 - Alpha
Classifier: Intended Audience :: Developers
Classifier: Intended Audience :: Information Technology
Classifier: License :: OSI Approved :: MIT License
Classifier: Natural Language :: English
Classifier: Operating System :: OS Independent
Classifier: Programming Language :: Python :: 3.7
Classifier: Programming Language :: Python :: 3.8
Classifier: Topic :: Communications
Classifier: Topic :: Software Development :: Libraries
Requires-Python: >=3.7
